{
  "SoapApi" : {
    "type" : "SOAP",
    "endpoint" : "http://10.207.159.26:19100/wsexistbus/ws/",
    "path" : "WS_TestTuxWinLettura",
    "name" : "WS_TestTuxWinLettura",
    "remoteName" : "WS_TestTuxWinLettura",
    "localPath" : "esb_tst5\\repo\\WS_TestTuxWinLettura",
    "authentication" : "Undefined",
    "apiSpecification" : {
      "apiSpecEndpoint" : "http://10.207.159.26:19100/wsexistbus/ws/WS_TestTuxWinLettura?WSDL",
      "xsdSchemas" : [ ]
    },
    "integrationScenario" : "DATA_MANIPULATION",
    "compressionSupported" : false,
    "bufferingSupported" : false
  }
}